<annotation>
  <folder>images</folder>
  <filename>frame_no_07260.jpg</filename>
  <path>/home/sami_malik914/Ahmer/EyeQ-Challenge/data/Person Tracking/images</path>
  <source>
    <database>Unknown</database>
  </source>
  <size>
    <width>1920</width>
    <height>1080</height>
    <depth>3</depth>
  </size>
  <segmented>0</segmented>
  <object>
    <name>1</name>
    <pose>Unspecified</pose>
    <truncated>0</truncated>
    <difficult>0</difficult>
    <bndbox>
      <xmin>1482</xmin>
      <ymin>685</ymin>
      <xmax>1762</xmax>
      <ymax>1067</ymax>
    </bndbox>
  </object>
  <object>
    <name>3</name>
    <pose>Unspecified</pose>
    <truncated>0</truncated>
    <difficult>0</difficult>
    <bndbox>
      <xmin>994</xmin>
      <ymin>153</ymin>
      <xmax>1059</xmax>
      <ymax>360</ymax>
    </bndbox>
  </object>
  <object>
    <name>4</name>
    <pose>Unspecified</pose>
    <truncated>0</truncated>
    <difficult>0</difficult>
    <bndbox>
      <xmin>316</xmin>
      <ymin>542</ymin>
      <xmax>641</xmax>
      <ymax>1069</ymax>
    </bndbox>
  </object>
  <object>
    <name>5</name>
    <pose>Unspecified</pose>
    <truncated>0</truncated>
    <difficult>0</difficult>
    <bndbox>
      <xmin>1425</xmin>
      <ymin>316</ymin>
      <xmax>1684</xmax>
      <ymax>706</ymax>
    </bndbox>
  </object>
  <object>
    <name>6</name>
    <pose>Unspecified</pose>
    <truncated>0</truncated>
    <difficult>0</difficult>
    <bndbox>
      <xmin>1077</xmin>
      <ymin>399</ymin>
      <xmax>1344</xmax>
      <ymax>784</ymax>
    </bndbox>
  </object>
  <object>
    <name>7</name>
    <pose>Unspecified</pose>
    <truncated>0</truncated>
    <difficult>0</difficult>
    <bndbox>
      <xmin>1080</xmin>
      <ymin>147</ymin>
      <xmax>1165</xmax>
      <ymax>386</ymax>
    </bndbox>
  </object>
</annotation>
